zdg/__init__.py
zdg/counter.py
zdg/graph.py
zdg/groupoid.py
zdg/semigroup.py
zdg/zdg.py
zdg/tests/__init__.py
zdg/tests/test_counter.py
zdg/tests/test_graph.py
zdg/tests/test_groupoid.py
zdg/tests/test_semigroup.py
zero_divisor_graph-1.0.0.dist-info/METADATA
zero_divisor_graph-1.0.0.dist-info/WHEEL
zero_divisor_graph-1.0.0.dist-info/top_level.txt
zero_divisor_graph-1.0.0.dist-info/RECORD
