Metadata-Version: 2.1
Name: zero-divisor-graph
Version: 1.0.0
Summary: a library for working with zero divisor graphs of commutative semigroups
Home-page: https://github.com/Paulcappaert/zero-divisor-graph
Author: Paul Cappaert
Author-email: paul.cappaert@gmail.com
License: MIT
Platform: UNKNOWN
Classifier: License :: OSI Approved :: MIT License
Classifier: Programming Language :: Python :: 3
Classifier: Programming Language :: Python :: 3.7
Requires-Dist: numpy
